mline/__init__.py
mline/__main__.py
mline/mline.py
mline-0.1.0.dist-info/LICENSE
mline-0.1.0.dist-info/METADATA
mline-0.1.0.dist-info/NOTICE
mline-0.1.0.dist-info/WHEEL
mline-0.1.0.dist-info/top_level.txt
mline-0.1.0.dist-info/RECORD
